Workbook

Sheet Assumptions
B2: Meta Journeys — NPV & Cost/Benefit Model
B3: ILLUSTRATIVE / MODELED — every figure below is an assumption, not measured data. Meta's internal costs are not public and Journeys is hypothetical. Adjust the blue inputs to test scenarios.
B5: Legend: Blue = input you can change · Black = formula · Green = links from another sheet · Yellow = key assumption
B7: GLOBAL ASSUMPTIONS
B8: Discount rate (WACC) | C8: 0.1
B9: Instagram MAU (billions) — base for adoption | C9: 2.4
B10: Long-run Journeys adoption ceiling (% of IG MAU) | C10: 0.095
B11: Net revenue margin to Meta (after creator/partner share) | C11: 1
B13: ADOPTION & MONETIZATION RAMP (modeled)
B14: Timeline (months) | C14: 0–12 | D14: 12–24 | E14: 24–36 | F14: 36–48 | G14: 48–60 | H14: 60–72 | I14: 72–84
B15: Year | C15: Year 0 | D15: Year 1 | E15: Year 2 | F15: Year 3 | G15: Year 4 | H15: Year 5 | I15: Year 6
B16: Active Journey users (millions) | C16: 5 | D16: 25 | E16: 60 | F16: 100 | G16: 140 | H16: 170 | I16: 190
B17: as % of IG MAU | C17: =C16/1000/$C$9 | D17: =D16/1000/$C$9 | E17: =E16/1000/$C$9 | F17: =F16/1000/$C$9 | G17: =G16/1000/$C$9 | H17: =H16/1000/$C$9 | I17: =I16/1000/$C$9
B18: Incremental net ARPU per Journey user ($/yr) | C18: 1 | D18: 4 | E18: 9 | F18: 14 | G18: 18 | H18: 21 | I18: 23
B19: ARPU ramp reflects monetization maturing: Yr0–1 mostly better ad targeting; Yr2+ sponsored labeled recommendations; Yr4+ commerce, affiliate & premium coaching layered in.
B20: Glasses ecosystem revenue ($mm) — upside layer | C20: 0 | D20: 0 | E20: 0 | F20: 50 | G20: 150 | H20: 300 | I20: 500
B22: HOW THE MODEL WORKS
B23: • Phase costs (next sheet) are mapped to calendar years and flow into the NPV cash flows.
B24: • Revenue = Journey users × incremental ARPU + glasses upside. Monetization begins in Year 1 (Phase 2).
B25: • Net cash flow = revenue − (phase build costs + ongoing run-rate). Discounted at the WACC above.
B26: • NPV excludes any terminal value beyond Year 6, making it deliberately conservative.
B27: • All inputs are illustrative. The structure and the per-phase logic are the point, not the precise figures.

Sheet Phase Cost-Benefit
B2: Cost & Benefit by Rollout Phase (illustrative)
B4: Phase | C4: Name | D4: Months | E4: Est. cost ($mm) | F4: Primary cost drivers (why) | G4: Primary benefit
B5: Phase 0 | C5: Seeded Closed Beta | D5: 0–3 | E5: 15 | F5: Small core eng/design team building the MVP (creation, story-style posts, off-grid container, viewer, in-journey AI). Founding Journeys creator program — incentive is amplification, low cash cost. | G5: Proves the core loop; sets cultural norms before scale. No revenue yet.
B6: Phase 1 | C6: Public Launch (Instagram) | D6: 3–9 | E6: 80 | F6: Scaling eng + infra to serve all IG users; the "Everyone Starts at Day One" hero campaign; Explore/feed/discovery integration; expanded creator waves. | G6: Validates loop at scale & cold-start mechanics. Still organic only — sets up monetization.
B7: Phase 2 | C7: Monetization + WhatsApp | D7: 9–15 | E7: 60 | F7: Sponsored-recommendation ad-tech build; cross-app WhatsApp integration (heavier engineering); continued marketing. | G7: Revenue begins (sponsored, labeled recs). WhatsApp lifts retention — the multiplier.
B8: Phase 3 | C8: Video Journeys in Reels | D8: 15–21 | E8: 30 | F8: Light eng — a badge + "view full journey?" button on existing Reels (format untouched); continued marketing & ongoing run-rate. | G8: Low-risk acquisition on-ramp from the highest-traffic surface.
B9: Phase 4 | C9: AI "Try This Out?" CTA in Reels | D9: 21–27 | E9: 70 | F9: AI integration into the crown-jewel Reels feed; heavy testing & risk-mitigation; guardrail monitoring of Reels core metrics. | G9: Turns Reels into a proactive acquisition engine — biggest funnel, highest risk.
B10: Phase 5 | C10: Facebook Expansion | D10: 27–36 | E10: 90 | F10: Genuine re-design for the Facebook surface (Groups integration, life-events framing) — not a reskin; FB-specific eng + marketing. | G10: Second native home, esp. for life-documentation journeys; higher-ARPU categories.
B11: Phase 6 | C11: Meta Glasses Coaching | D11: 36+ | E11: 120 | F11: Hardware integration & on-device AI coaching R&D; long horizon, highest uncertainty; ongoing multi-year investment. | G11: Closes the flywheel; the ecosystem moat. Opt-in; upside layer.
B12: TOTAL build | E12: =SUM(E5:E11)
B14: Note: phase costs are one-time build/launch investments. Ongoing run-rate (maintenance, infra at scale, moderation, sustaining marketing) is modeled separately in the NPV sheet and grows with the user base.

Sheet NPV Model
B2: NPV Analysis — 7-Year Cash Flow ($mm)
B4: ($ millions) | C4: Year 0 | D4: Year 1 | E4: Year 2 | F4: Year 3 | G4: Year 4 | H4: Year 5 | I4: Year 6
B6: REVENUE
B7: Journey users (millions) | C7: =Assumptions!C16 | D7: =Assumptions!D16 | E7: =Assumptions!E16 | F7: =Assumptions!F16 | G7: =Assumptions!G16 | H7: =Assumptions!H16 | I7: =Assumptions!I16
B8: Incremental ARPU ($/user/yr) | C8: =Assumptions!C18 | D8: =Assumptions!D18 | E8: =Assumptions!E18 | F8: =Assumptions!F18 | G8: =Assumptions!G18 | H8: =Assumptions!H18 | I8: =Assumptions!I18
B9: Core revenue (users × ARPU) | C9: =C7*C8 | D9: =D7*D8 | E9: =E7*E8 | F9: =F7*F8 | G9: =G7*G8 | H9: =H7*H8 | I9: =I7*I8
B10: Glasses ecosystem revenue (upside) | C10: =Assumptions!C20 | D10: =Assumptions!D20 | E10: =Assumptions!E20 | F10: =Assumptions!F20 | G10: =Assumptions!G20 | H10: =Assumptions!H20 | I10: =Assumptions!I20
B11: Total revenue | C11: =C9+C10 | D11: =D9+D10 | E11: =E9+E10 | F11: =F9+F10 | G11: =G9+G10 | H11: =H9+H10 | I11: =I9+I10
B13: COSTS
B14: Phase build / launch costs | C14: ='Phase Cost-Benefit'!E5+'Phase Cost-Benefit'!E6+0.5*'Phase Cost-Benefit'!E7 | D14: =0.5*'Phase Cost-Benefit'!E7+'Phase Cost-Benefit'!E8+0.5*'Phase Cost-Benefit'!E9 | E14: =0.5*'Phase Cost-Benefit'!E9+'Phase Cost-Benefit'!E10 | F14: ='Phase Cost-Benefit'!E11 | G14: =80 | H14: =60 | I14: =50
B15: Ongoing run-rate (ops, infra, sustaining mktg) | C15: 20 | D15: 50 | E15: 90 | F15: 120 | G15: 140 | H15: 150 | I15: 160
B16: Total costs | C16: =C14+C15 | D16: =D14+D15 | E16: =E14+E15 | F16: =F14+F15 | G16: =G14+G15 | H16: =H14+H15 | I16: =I14+I15
B18: NET CASH FLOW | C18: =C11-C16 | D18: =D11-D16 | E18: =E11-E16 | F18: =F11-F16 | G18: =G11-G16 | H18: =H11-H16 | I18: =I11-I16
B19: Discount factor @ WACC | C19: =1/(1+Assumptions!$C8)^0 | D19: =1/(1+Assumptions!$C8)^1 | E19: =1/(1+Assumptions!$C8)^2 | F19: =1/(1+Assumptions!$C8)^3 | G19: =1/(1+Assumptions!$C8)^4 | H19: =1/(1+Assumptions!$C8)^5 | I19: =1/(1+Assumptions!$C8)^6
B20: Discounted cash flow | C20: =C18*C19 | D20: =D18*D19 | E20: =E18*E19 | F20: =F18*F19 | G20: =G18*G19 | H20: =H18*H19 | I20: =I18*I19
B21: Cumulative discounted cash flow | C21: =C20 | D21: =C21+D20 | E21: =D21+E20 | F21: =E21+F20 | G21: =F21+G20 | H21: =G21+H20 | I21: =H21+I20
B23: KEY OUTPUTS
B24: NPV (7-yr, excl. terminal value) | D24: =SUM(C20:I20)
B25: Undiscounted cumulative net cash flow | D25: =SUM(C18:I18)
B26: Total revenue (7-yr) | D26: =SUM(C11:I11)
B27: Total investment (7-yr) | D27: =SUM(C16:I16)
B28: IRR (annual) | D28: =IRR(C18:I18)
B29: Benefit/Cost ratio (PV rev ÷ PV cost) | D29: =SUMPRODUCT(C11:I11,C19:I19)/SUMPRODUCT(C16:I16,C19:I19)
B31: All figures illustrative/modeled. NPV excludes terminal value beyond Year 6 (conservative). Change blue inputs on Assumptions to run scenarios; the Sensitivity sheet shows NPV across adoption and ARPU cases.

Sheet Sensitivity
B2: Sensitivity — NPV drivers ($mm)
B4: The base-case NPV is highly sensitive to two modeled drivers: adoption (how many users start Journeys) and mature ARPU (how well it monetizes). The grid below illustrates directional ranges — recompute by changing the blue inputs on the Assumptions sheet. These are static reference points, not live-linked.
B6: Base-case NPV (from NPV Model) | D6: ='NPV Model'!D24
B8: Illustrative scenario NPVs (modeled)
B9: Scenario | C9: Peak users (mm) | D9: Mature ARPU ($) | E9: Approx. NPV ($mm) | F9: Read
B10: Bear (slow adoption, weak monetization) | C10: 90 | D10: 10 | E10: 2100 | F10: Still strongly NPV-positive — low downside.
B11: Base case | C11: 190 | D11: 23 | E11: 7573 | F11: Central estimate used in the model.
B12: Bull (fast adoption, commerce + glasses land) | C12: 260 | D12: 32 | E12: 14500 | F12: Ecosystem flywheel fully realized.
B14: Discount-rate sensitivity (base-case cash flows)
B15: WACC | C15: 8% | D15: 10% (base) | E15: 12% | F15: 15%
B16: Approx. NPV ($mm) | C16: 8600 | D16: 7573 | E16: 6700 | F16: 5500
B18: Even in the bear case and at a high discount rate, the project stays clearly NPV-positive — because it rides existing infrastructure and the existing social graph, so incremental cost is modest relative to the revenue an at-scale Instagram feature can unlock. The risk is not negative NPV; it is adoption falling short of the threshold where the loop sustains.
